mqdq/__init__.py
mqdq/babble.py
mqdq/elegy.py
mqdq/hexameter_corpus.py
mqdq/line_analyzer.py
mqdq/mahalanobis.py
mqdq/ngrams.py
mqdq/rhyme.py
mqdq/rhyme_classes.py
mqdq/utils.py
mqdq/cltk_hax/scansion_constants.py
mqdq/cltk_hax/string_utils.py
mqdq/cltk_hax/syllabifier.py
MQDQParser-0.6.2.dist-info/LICENSE.txt
MQDQParser-0.6.2.dist-info/METADATA
MQDQParser-0.6.2.dist-info/WHEEL
MQDQParser-0.6.2.dist-info/top_level.txt
MQDQParser-0.6.2.dist-info/RECORD
