Metadata-Version: 2.1
Name: MQDQParser
Version: 0.6.2
Summary: UNKNOWN
Home-page: https://github.com/bnagy/mqdq-parser
Author: Ben Nagy
License: 3-Clause BSD
Platform: UNKNOWN
License-File: LICENSE.txt
Requires-Dist: setuptools
Requires-Dist: beautifulsoup4
Requires-Dist: lxml
Requires-Dist: numpy
Requires-Dist: scipy
Requires-Dist: pandas
Requires-Dist: seaborn
Requires-Dist: dominate
